typechecked/__init__.py
typechecked/_cache.py
typechecked/_check_result.py
typechecked/_constants.py
typechecked/_generic.py
typechecked/_log.py
typechecked/_meta.py
typechecked/_options.py
typechecked/_primitives.py
typechecked/_typechecked.py
typechecked/_types.py
typechecked/_validate.py
typechecked/_validation_state.py
typechecked/py.typed
typechecked/_collections_abc/__init__.py
typechecked/_collections_abc/_callable.py
typechecked/_collections_abc/_collection.py
typechecked/_collections_abc/_iterable.py
typechecked/_collections_abc/_mapping.py
typechecked/_collections_abc/_sequence.py
typechecked/_collections_abc/_set.py
typechecked/_doc_utils/__init__.py
typechecked/_doc_utils/_enum_docstrings.py
typechecked/_doc_utils/_format_docstring.py
typechecked/_error_tags/__init__.py
typechecked/_error_tags/_type_hints.py
typechecked/_error_tags/_typed_dict_key_info.py
typechecked/_exceptions/__init__.py
typechecked/_exceptions/_error_tag.py
typechecked/_exceptions/_tagged_exception.py
typechecked/_exceptions/_type_check_error.py
typechecked/_immutable/__init__.py
typechecked/_immutable/_error_tags.py
typechecked/_immutable/_immutable.py
typechecked/_immutable/_protocol.py
typechecked/_typing/__init__.py
typechecked/_typing/_literal.py
typechecked/_typing/_typeddict.py
typechecked/_typing/_typeddict_key_info.py
typechecked/_typing/_union.py
typechecked/_validation_cache/__init__.py
typechecked/_validation_cache/_cache.py
typechecked/_validation_cache/_cache_entry.py
typechecked/_validation_cache/_cache_key.py
typechecked/_validation_cache/_error_tags.py
typechecked-0.11.1.dist-info/METADATA
typechecked-0.11.1.dist-info/WHEEL
typechecked-0.11.1.dist-info/licenses/LICENSE
typechecked-0.11.1.dist-info/RECORD
