Metadata-Version: 2.4
Name: typechecked
Version: 0.11.1
Summary: Runtime type checking using type hints.
Project-URL: Homepage, https://github.com/JerilynFranz/python-typechecked
Project-URL: Documentation, https://python-typechecked.readthedocs.io/en/latest/
Project-URL: Repository, https://github.com/JerilynFranz/python-typechecked.git
Project-URL: Issues, https://github.com/JerilynFranz/python-typechecked/issues
Project-URL: Changelog, https://github.com/JerilynFranz/python-typechecked/blob/main/CHANGELOG.rst
Author-email: Jerilyn Franz <opensource@snowhare.com>
Maintainer-email: Jerilyn Franz <opensource@snowhare.com>
License-File: LICENSE
Keywords: developer-tools,python,runtime,runtime-validation,static-analysis,type-checked,type-checking,type-enforcement,type-hints,type-safety,typechecked,typechecking,typehint,typing,validation
Classifier: Development Status :: 4 - Beta
Classifier: Intended Audience :: Developers
Classifier: License :: OSI Approved :: Apache Software License
Classifier: Operating System :: MacOS :: MacOS X
Classifier: Operating System :: Microsoft :: Windows
Classifier: Operating System :: OS Independent
Classifier: Operating System :: POSIX :: Linux
Classifier: Programming Language :: Python
Classifier: Programming Language :: Python :: 3
Classifier: Programming Language :: Python :: 3.10
Classifier: Programming Language :: Python :: 3.11
Classifier: Programming Language :: Python :: 3.12
Classifier: Programming Language :: Python :: 3.13
Classifier: Programming Language :: Python :: 3.14
Classifier: Programming Language :: Python :: Implementation :: CPython
Classifier: Programming Language :: Python :: Implementation :: PyPy
Classifier: Topic :: Software Development
Classifier: Typing :: Typed
Requires-Python: >=3.10
Requires-Dist: typing-extensions>=4.10.0
